easy_logging/__init__.py
easy_logging/easy_logger.py
easy_logging-0.0.1.dist-info/LICENSE
easy_logging-0.0.1.dist-info/METADATA
easy_logging-0.0.1.dist-info/WHEEL
easy_logging-0.0.1.dist-info/top_level.txt
easy_logging-0.0.1.dist-info/RECORD
